Metadata-Version: 1.1
Name: cdumay-env2cfgfile
Version: 0.0.2
Summary: Lib to dump environment variables into a configuration file
Home-page: https://github.com/cdumay/cdumay-env2cfgfile
Author: Cedric DUMAY
Author-email: cedric.dumay@gmail.com
License: MIT
Platform: UNKNOWN
Classifier: Programming Language :: Python
